judo/__init__.py
judo/config.yml
judo/data_types.py
judo/judo_backend.py
judo/judo_tensor.py
judo/typing.py
judo/version.py
judo/data_structures/__init__.py
judo/data_structures/bounds.py
judo/data_structures/memory.py
judo/data_structures/states.py
judo/data_structures/tree.py
judo/functions/__init__.py
judo/functions/api.py
judo/functions/batching.py
judo/functions/fractalai.py
judo/functions/hashing.py
judo/functions/images.py
judo/functions/notebook.py
judo/functions/numpy.py
judo/functions/pytorch.py
judo/functions/random.py
tests/__init__.py
tests/test_api.py
tests/test_backend.py
tests/test_bounds.py
tests/test_states.py
tests/test_tree.py
tests/test_types.py
tests/functions/__init__.py
tests/functions/test_images.py
tests/functions/test_notebook.py
judo-0.0.15.dist-info/LICENSE
judo-0.0.15.dist-info/METADATA
judo-0.0.15.dist-info/WHEEL
judo-0.0.15.dist-info/top_level.txt
judo-0.0.15.dist-info/RECORD
