Metadata-Version: 2.1
Name: judo
Version: 0.0.15
Summary: API and data structures for efficient AI research.
Home-page: https://github.com/FragileTech/judo
Author: FragileTech
Author-email: info@fragile.tech
License: MIT
Keywords: Machine learning,artificial intelligence
Classifier: Development Status :: 3 - Alpha
Classifier: Intended Audience :: Developers
Classifier: License :: OSI Approved :: MIT License
Classifier: Programming Language :: Python :: 3.6
Classifier: Programming Language :: Python :: 3.7
Classifier: Programming Language :: Python :: 3.8
Classifier: Programming Language :: Python :: 3.9
Classifier: Topic :: Software Development :: Libraries
License-File: LICENSE
Requires-Dist: numpy (>=1.0.0)
Requires-Dist: pyyaml (>=5.0.0)
Requires-Dist: xxhash (>=1.1.0)
Provides-Extra: all
Requires-Dist: torch (>=1.0.0) ; extra == 'all'
Requires-Dist: pillow (>=7.0.0) ; extra == 'all'
Requires-Dist: ipython (>=7.0.0) ; extra == 'all'
Requires-Dist: networkx (>2.0.0) ; extra == 'all'
Provides-Extra: data-structures
Requires-Dist: networkx (>2.0.0) ; extra == 'data-structures'
Provides-Extra: image
Requires-Dist: pillow (>=7.0.0) ; extra == 'image'
Provides-Extra: ipython
Requires-Dist: ipython (>=7.0.0) ; extra == 'ipython'
Provides-Extra: torch
Requires-Dist: torch (>=1.0.0) ; extra == 'torch'
